Workbook

Sheet Executive Summary
A1: AI Prior Authorization Platform — Market Opportunity Summary
A2: US + Canada Healthcare — TAM / SAM / SOM (US$, unless noted). All figures link live to the underlying model.
B4: Geography | C4: Software TAM ($B) | D4: SAM ($B) | E4: SOM — Base ($B) | F4: SOM — Upside ($B)
B5: United States | C5: ='US National Model'!C13 -> 12.96 | D5: ='US National Model'!C16 -> 5.184 | E5: ='US National Model'!C19 -> 0.07776 | F5: ='US National Model'!C21 -> 0.15552
B6: Canada | C6: ='Canada National Model'!D13 -> 0.44318592 | D6: ='Canada National Model'!D16 -> 0.17727437 | E6: ='Canada National Model'!D19 -> 0.0026591155 | F6: ='Canada National Model'!D21 -> 0.005318231
B7: US + CANADA COMBINED | C7: =SUM(C5:C6) -> 13.403186 | D7: =SUM(D5:D6) -> 5.3612744 | E7: =SUM(E5:E6) -> 0.080419116 | F7: =SUM(F5:F6) -> 0.16083823
B10: Top 10 US states by opportunity (base-case SOM)
B11: State | C11: TAM ($M) | D11: SAM ($M) | E11: SOM — Base ($M) | F11: SOM — Upside ($M)
B12: California | C12: {=INDEX('US State Breakdown'!$G$5:$G$55,MATCH($B12,'US State Breakdown'!$B$5:$B$55,0))} -> 1578.1651 | D12: {=INDEX('US State Breakdown'!$H$5:$H$55,MATCH($B12,'US State Breakdown'!$B$5:$B$55,0))} -> 631.26605 | E12: {=INDEX('US State Breakdown'!$I$5:$I$55,MATCH($B12,'US State Breakdown'!$B$5:$B$55,0))} -> 9.4689908 | F12: {=INDEX('US State Breakdown'!$J$5:$J$55,MATCH($B12,'US State Breakdown'!$B$5:$B$55,0))} -> 18.937982
B13: Texas | C13: {=INDEX('US State Breakdown'!$G$5:$G$55,MATCH($B13,'US State Breakdown'!$B$5:$B$55,0))} -> 1085.6389 | D13: {=INDEX('US State Breakdown'!$H$5:$H$55,MATCH($B13,'US State Breakdown'!$B$5:$B$55,0))} -> 434.25555 | E13: {=INDEX('US State Breakdown'!$I$5:$I$55,MATCH($B13,'US State Breakdown'!$B$5:$B$55,0))} -> 6.5138332 | F13: {=INDEX('US State Breakdown'!$J$5:$J$55,MATCH($B13,'US State Breakdown'!$B$5:$B$55,0))} -> 13.027666
B14: New York | C14: {=INDEX('US State Breakdown'!$G$5:$G$55,MATCH($B14,'US State Breakdown'!$B$5:$B$55,0))} -> 935.64574 | D14: {=INDEX('US State Breakdown'!$H$5:$H$55,MATCH($B14,'US State Breakdown'!$B$5:$B$55,0))} -> 374.2583 | E14: {=INDEX('US State Breakdown'!$I$5:$I$55,MATCH($B14,'US State Breakdown'!$B$5:$B$55,0))} -> 5.6138745 | F14: {=INDEX('US State Breakdown'!$J$5:$J$55,MATCH($B14,'US State Breakdown'!$B$5:$B$55,0))} -> 11.227749
B15: Florida | C15: {=INDEX('US State Breakdown'!$G$5:$G$55,MATCH($B15,'US State Breakdown'!$B$5:$B$55,0))} -> 919.84482 | D15: {=INDEX('US State Breakdown'!$H$5:$H$55,MATCH($B15,'US State Breakdown'!$B$5:$B$55,0))} -> 367.93793 | E15: {=INDEX('US State Breakdown'!$I$5:$I$55,MATCH($B15,'US State Breakdown'!$B$5:$B$55,0))} -> 5.5190689 | F15: {=INDEX('US State Breakdown'!$J$5:$J$55,MATCH($B15,'US State Breakdown'!$B$5:$B$55,0))} -> 11.038138
B16: Pennsylvania | C16: {=INDEX('US State Breakdown'!$G$5:$G$55,MATCH($B16,'US State Breakdown'!$B$5:$B$55,0))} -> 530.10162 | D16: {=INDEX('US State Breakdown'!$H$5:$H$55,MATCH($B16,'US State Breakdown'!$B$5:$B$55,0))} -> 212.04065 | E16: {=INDEX('US State Breakdown'!$I$5:$I$55,MATCH($B16,'US State Breakdown'!$B$5:$B$55,0))} -> 3.1806097 | F16: {=INDEX('US State Breakdown'!$J$5:$J$55,MATCH($B16,'US State Breakdown'!$B$5:$B$55,0))} -> 6.3612195
B17: Illinois | C17: {=INDEX('US State Breakdown'!$G$5:$G$55,MATCH($B17,'US State Breakdown'!$B$5:$B$55,0))} -> 475.87749 | D17: {=INDEX('US State Breakdown'!$H$5:$H$55,MATCH($B17,'US State Breakdown'!$B$5:$B$55,0))} -> 190.35099 | E17: {=INDEX('US State Breakdown'!$I$5:$I$55,MATCH($B17,'US State Breakdown'!$B$5:$B$55,0))} -> 2.8552649 | F17: {=INDEX('US State Breakdown'!$J$5:$J$55,MATCH($B17,'US State Breakdown'!$B$5:$B$55,0))} -> 5.7105298
B18: Ohio | C18: {=INDEX('US State Breakdown'!$G$5:$G$55,MATCH($B18,'US State Breakdown'!$B$5:$B$55,0))} -> 458.61209 | D18: {=INDEX('US State Breakdown'!$H$5:$H$55,MATCH($B18,'US State Breakdown'!$B$5:$B$55,0))} -> 183.44484 | E18: {=INDEX('US State Breakdown'!$I$5:$I$55,MATCH($B18,'US State Breakdown'!$B$5:$B$55,0))} -> 2.7516725 | F18: {=INDEX('US State Breakdown'!$J$5:$J$55,MATCH($B18,'US State Breakdown'!$B$5:$B$55,0))} -> 5.5033451
B19: New Jersey | C19: {=INDEX('US State Breakdown'!$G$5:$G$55,MATCH($B19,'US State Breakdown'!$B$5:$B$55,0))} -> 402.73079 | D19: {=INDEX('US State Breakdown'!$H$5:$H$55,MATCH($B19,'US State Breakdown'!$B$5:$B$55,0))} -> 161.09231 | E19: {=INDEX('US State Breakdown'!$I$5:$I$55,MATCH($B19,'US State Breakdown'!$B$5:$B$55,0))} -> 2.4163847 | F19: {=INDEX('US State Breakdown'!$J$5:$J$55,MATCH($B19,'US State Breakdown'!$B$5:$B$55,0))} -> 4.8327694
B20: Michigan | C20: {=INDEX('US State Breakdown'!$G$5:$G$55,MATCH($B20,'US State Breakdown'!$B$5:$B$55,0))} -> 389.24219 | D20: {=INDEX('US State Breakdown'!$H$5:$H$55,MATCH($B20,'US State Breakdown'!$B$5:$B$55,0))} -> 155.69688 | E20: {=INDEX('US State Breakdown'!$I$5:$I$55,MATCH($B20,'US State Breakdown'!$B$5:$B$55,0))} -> 2.3354532 | F20: {=INDEX('US State Breakdown'!$J$5:$J$55,MATCH($B20,'US State Breakdown'!$B$5:$B$55,0))} -> 4.6709063
B21: North Carolina | C21: {=INDEX('US State Breakdown'!$G$5:$G$55,MATCH($B21,'US State Breakdown'!$B$5:$B$55,0))} -> 381.53443 | D21: {=INDEX('US State Breakdown'!$H$5:$H$55,MATCH($B21,'US State Breakdown'!$B$5:$B$55,0))} -> 152.61377 | E21: {=INDEX('US State Breakdown'!$I$5:$I$55,MATCH($B21,'US State Breakdown'!$B$5:$B$55,0))} -> 2.2892066 | F21: {=INDEX('US State Breakdown'!$J$5:$J$55,MATCH($B21,'US State Breakdown'!$B$5:$B$55,0))} -> 4.5784131
B24: Top 5 Canadian provinces by opportunity (base-case SOM)
B25: Province | C25: TAM (US$M) | D25: SAM (US$M) | E25: SOM — Base (US$M) | F25: SOM — Upside (US$M)
B26: Ontario | C26: {=INDEX('Canada Province Breakdown'!$G$5:$G$17,MATCH($B26,'Canada Province Breakdown'!$B$5:$B$17,0))} -> 165.15808 | D26: {=INDEX('Canada Province Breakdown'!$H$5:$H$17,MATCH($B26,'Canada Province Breakdown'!$B$5:$B$17,0))} -> 66.063232 | E26: {=INDEX('Canada Province Breakdown'!$I$5:$I$17,MATCH($B26,'Canada Province Breakdown'!$B$5:$B$17,0))} -> 0.99094848 | F26: {=INDEX('Canada Province Breakdown'!$J$5:$J$17,MATCH($B26,'Canada Province Breakdown'!$B$5:$B$17,0))} -> 1.981897
B27: Quebec | C27: {=INDEX('Canada Province Breakdown'!$G$5:$G$17,MATCH($B27,'Canada Province Breakdown'!$B$5:$B$17,0))} -> 97.928509 | D27: {=INDEX('Canada Province Breakdown'!$H$5:$H$17,MATCH($B27,'Canada Province Breakdown'!$B$5:$B$17,0))} -> 39.171404 | E27: {=INDEX('Canada Province Breakdown'!$I$5:$I$17,MATCH($B27,'Canada Province Breakdown'!$B$5:$B$17,0))} -> 0.58757105 | F27: {=INDEX('Canada Province Breakdown'!$J$5:$J$17,MATCH($B27,'Canada Province Breakdown'!$B$5:$B$17,0))} -> 1.1751421
B28: British Columbia | C28: {=INDEX('Canada Province Breakdown'!$G$5:$G$17,MATCH($B28,'Canada Province Breakdown'!$B$5:$B$17,0))} -> 61.617938 | D28: {=INDEX('Canada Province Breakdown'!$H$5:$H$17,MATCH($B28,'Canada Province Breakdown'!$B$5:$B$17,0))} -> 24.647175 | E28: {=INDEX('Canada Province Breakdown'!$I$5:$I$17,MATCH($B28,'Canada Province Breakdown'!$B$5:$B$17,0))} -> 0.36970763 | F28: {=INDEX('Canada Province Breakdown'!$J$5:$J$17,MATCH($B28,'Canada Province Breakdown'!$B$5:$B$17,0))} -> 0.73941526
B29: Alberta | C29: {=INDEX('Canada Province Breakdown'!$G$5:$G$17,MATCH($B29,'Canada Province Breakdown'!$B$5:$B$17,0))} -> 51.759068 | D29: {=INDEX('Canada Province Breakdown'!$H$5:$H$17,MATCH($B29,'Canada Province Breakdown'!$B$5:$B$17,0))} -> 20.703627 | E29: {=INDEX('Canada Province Breakdown'!$I$5:$I$17,MATCH($B29,'Canada Province Breakdown'!$B$5:$B$17,0))} -> 0.31055441 | F29: {=INDEX('Canada Province Breakdown'!$J$5:$J$17,MATCH($B29,'Canada Province Breakdown'!$B$5:$B$17,0))} -> 0.62110882
B30: Manitoba | C30: {=INDEX('Canada Province Breakdown'!$G$5:$G$17,MATCH($B30,'Canada Province Breakdown'!$B$5:$B$17,0))} -> 17.330045 | D30: {=INDEX('Canada Province Breakdown'!$H$5:$H$17,MATCH($B30,'Canada Province Breakdown'!$B$5:$B$17,0))} -> 6.932018 | E30: {=INDEX('Canada Province Breakdown'!$I$5:$I$17,MATCH($B30,'Canada Province Breakdown'!$B$5:$B$17,0))} -> 0.10398027 | F30: {=INDEX('Canada Province Breakdown'!$J$5:$J$17,MATCH($B30,'Canada Province Breakdown'!$B$5:$B$17,0))} -> 0.20796054
B33: Note: 'Software TAM' = realistic vendor-capturable technology spend, derived from the full prior-auth/UM administrative cost pool via a 12% software-capture assumption (see Methodology + Assumptions tabs). SOM reflects a 1.5% (base) to 3.0% (upside) share of SAM captured within a 3–5 year horizon, consistent with a focused new entrant competing against Cohere Health, Rhyme, Availity, Waystar, Myndshft, and XSOLIS.

Sheet License Pricing & Breakeven
A1: ClearAuth AI — License Pricing Tiers & Product Investment Break-Even
A2: Built from the client's own Onboarding Cost & ROI Model (uploaded PDF). All figures are live formulas — edit any yellow cell.
B4: SHARED ASSUMPTIONS (source: ClearAuth AI Onboarding Cost & ROI Model, client PDF)
B5: PA volume per physician, low (per month) | C5: 160
B6: PA volume per physician, high (per month) | C6: 175
B7: Manual administrative cost per PA, low ($) | C7: 20
B8: Manual administrative cost per PA, high ($) | C8: 30
B9: Automation handling-time reduction | C9: 0.75
B10: Conservative realization factor | C10: 0.5
B11: Onboarding labor rate ($/hour) | C11: 50
B12: Onboarding implementation contingency | C12: 0.15
B13: Electronic payer routes per practice (E) | C13: 3
B14: Payer portal routes per practice (B) | C14: 2
B15: License fee — % of conservative monthly savings captured | C15: 0.2
B16: PA-volume, manual-cost, automation-reduction, realization-factor, labor-rate, contingency, and route-count figures are taken directly from the client's uploaded Onboarding Cost & ROI Model. The license-fee capture rate (last row) is a new commercial assumption — this model prices the recurring subscription as a share of the monthly savings ClearAuth delivers, on top of the existing one-time onboarding fee.
B19: ITEM 1 — RECURRING LICENSE PRICING BY PRACTICE SIZE
B20: Practice Size (Physicians) | C20: Monthly PA Volume — Low | D20: Monthly PA Volume — High | E20: Monthly Manual Burden — Low | F20: Monthly Manual Burden — High | G20: Conservative Monthly Savings — Low | H20: Conservative Monthly Savings — High | I20: Recommended License Fee ($/mo) | J20: Per-Physician Rate ($/mo) | K20: One-Time Onboarding Price (ref.)
B21: 10 | C21: =$B21*$C$5 -> 1600 | D21: =$B21*$C$6 -> 1750 | E21: =C21*$C$7 -> 32000 | F21: =D21*$C$8 -> 52500 | G21: =E21*$C$9*$C$10 -> 12000 | H21: =F21*$C$9*$C$10 -> 19687.5 | I21: =AVERAGE(G21:H21)*$C$15 -> 3168.75 | J21: =I21/B21 -> 316.875 | K21: =(34+0.25*B21+3*$C$13+4*$C$14)*$C$11*(1+$C$12) -> 3076.25
B22: 25 | C22: =$B22*$C$5 -> 4000 | D22: =$B22*$C$6 -> 4375 | E22: =C22*$C$7 -> 80000 | F22: =D22*$C$8 -> 131250 | G22: =E22*$C$9*$C$10 -> 30000 | H22: =F22*$C$9*$C$10 -> 49218.75 | I22: =AVERAGE(G22:H22)*$C$15 -> 7921.875 | J22: =I22/B22 -> 316.875 | K22: =(34+0.25*B22+3*$C$13+4*$C$14)*$C$11*(1+$C$12) -> 3291.875
B23: 50 | C23: =$B23*$C$5 -> 8000 | D23: =$B23*$C$6 -> 8750 | E23: =C23*$C$7 -> 160000 | F23: =D23*$C$8 -> 262500 | G23: =E23*$C$9*$C$10 -> 60000 | H23: =F23*$C$9*$C$10 -> 98437.5 | I23: =AVERAGE(G23:H23)*$C$15 -> 15843.75 | J23: =I23/B23 -> 316.875 | K23: =(34+0.25*B23+3*$C$13+4*$C$14)*$C$11*(1+$C$12) -> 3651.25
B24: 100 | C24: =$B24*$C$5 -> 16000 | D24: =$B24*$C$6 -> 17500 | E24: =C24*$C$7 -> 320000 | F24: =D24*$C$8 -> 525000 | G24: =E24*$C$9*$C$10 -> 120000 | H24: =F24*$C$9*$C$10 -> 196875 | I24: =AVERAGE(G24:H24)*$C$15 -> 31687.5 | J24: =I24/B24 -> 316.875 | K24: =(34+0.25*B24+3*$C$13+4*$C$14)*$C$11*(1+$C$12) -> 4370
B25: License fee = 20% of the midpoint conservative monthly savings for that practice size (i.e., ClearAuth keeps ~20% of the value delivered as recurring subscription revenue; the client keeps ~80%). Per-physician rate lands at roughly the same $ figure across tiers because savings scale near-linearly with PA volume — this is what makes per-physician pricing viable rather than a flat per-practice fee. Onboarding price (one-time) reuses the exact formula from the client's own ROI model: H = 34 + 0.25P + 3E + 4B, Cost = H x $50/hr, Quoted = Cost x 1.15.
B29: ITEM 2 — PRODUCT BUILD INVESTMENT: BREAK-EVEN ANALYSIS
B30: One-time product build investment ($) | C30: 75000
B31: Fixed monthly cost — managed services + cloud ($/mo) | C31: 3000
B32: New customers per month — Conservative scenario | C32: 1
B33: New customers per month — Base scenario | C33: 2
B34: New customers per month — Aggressive scenario | C34: 3
B35: Customer profile assumed for all three scenarios below: the 'Standard 10-physician practice' from Item 1 above — one-time onboarding fee plus recurring license fee, both computed there. Each scenario differs only in how many new practices sign per month; no churn is modeled.
B38: Scenario | C38: New customers / mo | D38: Break-even month
B39: Conservative | C39: =$C$32 -> 1 | D39: =IF(J69<$C$30,">24 months",COUNTIF(J46:J69,"<"&$C$30)+1) -> 7
B40: Base | C40: =$C$33 -> 2 | D40: =IF(J97<$C$30,">24 months",COUNTIF(J74:J97,"<"&$C$30)+1) -> 4
B41: Aggressive | C41: =$C$34 -> 3 | D41: =IF(J125<$C$30,">24 months",COUNTIF(J102:J125,"<"&$C$30)+1) -> 3
B44: CONSERVATIVE SCENARIO — Conservative new customer(s)/month (detail)
B45: Month | C45: New Customers | D45: Cumulative Customers | E45: Onboarding Revenue | F45: Recurring License Revenue | G45: Total Revenue | H45: Fixed Opex (Mgd Svcs+Cloud) | I45: Net Cash Flow | J45: Cumulative Net Cash Flow
B46: 1 | C46: =$C$32 -> 1 | D46: =C46 -> 1 | E46: =C46*$K$21 -> 3076.25 | F46: =D46*$I$21 -> 3168.75 | G46: =E46+F46 -> 6245 | H46: =$C$31 -> 3000 | I46: =G46-H46 -> 3245 | J46: =I46 -> 3245
B47: 2 | C47: =$C$32 -> 1 | D47: =D46+C47 -> 2 | E47: =C47*$K$21 -> 3076.25 | F47: =D47*$I$21 -> 6337.5 | G47: =E47+F47 -> 9413.75 | H47: =$C$31 -> 3000 | I47: =G47-H47 -> 6413.75 | J47: =J46+I47 -> 9658.75
B48: 3 | C48: =$C$32 -> 1 | D48: =D47+C48 -> 3 | E48: =C48*$K$21 -> 3076.25 | F48: =D48*$I$21 -> 9506.25 | G48: =E48+F48 -> 12582.5 | H48: =$C$31 -> 3000 | I48: =G48-H48 -> 9582.5 | J48: =J47+I48 -> 19241.25
B49: 4 | C49: =$C$32 -> 1 | D49: =D48+C49 -> 4 | E49: =C49*$K$21 -> 3076.25 | F49: =D49*$I$21 -> 12675 | G49: =E49+F49 -> 15751.25 | H49: =$C$31 -> 3000 | I49: =G49-H49 -> 12751.25 | J49: =J48+I49 -> 31992.5
B50: 5 | C50: =$C$32 -> 1 | D50: =D49+C50 -> 5 | E50: =C50*$K$21 -> 3076.25 | F50: =D50*$I$21 -> 15843.75 | G50: =E50+F50 -> 18920 | H50: =$C$31 -> 3000 | I50: =G50-H50 -> 15920 | J50: =J49+I50 -> 47912.5
B51: 6 | C51: =$C$32 -> 1 | D51: =D50+C51 -> 6 | E51: =C51*$K$21 -> 3076.25 | F51: =D51*$I$21 -> 19012.5 | G51: =E51+F51 -> 22088.75 | H51: =$C$31 -> 3000 | I51: =G51-H51 -> 19088.75 | J51: =J50+I51 -> 67001.25
B52: 7 | C52: =$C$32 -> 1 | D52: =D51+C52 -> 7 | E52: =C52*$K$21 -> 3076.25 | F52: =D52*$I$21 -> 22181.25 | G52: =E52+F52 -> 25257.5 | H52: =$C$31 -> 3000 | I52: =G52-H52 -> 22257.5 | J52: =J51+I52 -> 89258.75
B53: 8 | C53: =$C$32 -> 1 | D53: =D52+C53 -> 8 | E53: =C53*$K$21 -> 3076.25 | F53: =D53*$I$21 -> 25350 | G53: =E53+F53 -> 28426.25 | H53: =$C$31 -> 3000 | I53: =G53-H53 -> 25426.25 | J53: =J52+I53 -> 114685
B54: 9 | C54: =$C$32 -> 1 | D54: =D53+C54 -> 9 | E54: =C54*$K$21 -> 3076.25 | F54: =D54*$I$21 -> 28518.75 | G54: =E54+F54 -> 31595 | H54: =$C$31 -> 3000 | I54: =G54-H54 -> 28595 | J54: =J53+I54 -> 143280
B55: 10 | C55: =$C$32 -> 1 | D55: =D54+C55 -> 10 | E55: =C55*$K$21 -> 3076.25 | F55: =D55*$I$21 -> 31687.5 | G55: =E55+F55 -> 34763.75 | H55: =$C$31 -> 3000 | I55: =G55-H55 -> 31763.75 | J55: =J54+I55 -> 175043.75
B56: 11 | C56: =$C$32 -> 1 | D56: =D55+C56 -> 11 | E56: =C56*$K$21 -> 3076.25 | F56: =D56*$I$21 -> 34856.25 | G56: =E56+F56 -> 37932.5 | H56: =$C$31 -> 3000 | I56: =G56-H56 -> 34932.5 | J56: =J55+I56 -> 209976.25
B57: 12 | C57: =$C$32 -> 1 | D57: =D56+C57 -> 12 | E57: =C57*$K$21 -> 3076.25 | F57: =D57*$I$21 -> 38025 | G57: =E57+F57 -> 41101.25 | H57: =$C$31 -> 3000 | I57: =G57-H57 -> 38101.25 | J57: =J56+I57 -> 248077.5
B58: 13 | C58: =$C$32 -> 1 | D58: =D57+C58 -> 13 | E58: =C58*$K$21 -> 3076.25 | F58: =D58*$I$21 -> 41193.75 | G58: =E58+F58 -> 44270 | H58: =$C$31 -> 3000 | I58: =G58-H58 -> 41270 | J58: =J57+I58 -> 289347.5
... B69: 24 | C69: =$C$32 -> 1 | D69: =D68+C69 -> 24 | E69: =C69*$K$21 -> 3076.25 | F69: =D69*$I$21 -> 76050 | G69: =E69+F69 -> 79126.25 | H69: =$C$31 -> 3000 | I69: =G69-H69 -> 76126.25 | J69: =J68+I69 -> 952455
B72: BASE SCENARIO — Base new customer(s)/month (detail)
B73: Month | C73: New Customers | D73: Cumulative Customers | E73: Onboarding Revenue | F73: Recurring License Revenue | G73: Total Revenue | H73: Fixed Opex (Mgd Svcs+Cloud) | I73: Net Cash Flow | J73: Cumulative Net Cash Flow
B74: 1 | C74: =$C$33 -> 2 | D74: =C74 -> 2 | E74: =C74*$K$21 -> 6152.5 | F74: =D74*$I$21 -> 6337.5 | G74: =E74+F74 -> 12490 | H74: =$C$31 -> 3000 | I74: =G74-H74 -> 9490 | J74: =I74 -> 9490
B75: 2 | C75: =$C$33 -> 2 | D75: =D74+C75 -> 4 | E75: =C75*$K$21 -> 6152.5 | F75: =D75*$I$21 -> 12675 | G75: =E75+F75 -> 18827.5 | H75: =$C$31 -> 3000 | I75: =G75-H75 -> 15827.5 | J75: =J74+I75 -> 25317.5
B76: 3 | C76: =$C$33 -> 2 | D76: =D75+C76 -> 6 | E76: =C76*$K$21 -> 6152.5 | F76: =D76*$I$21 -> 19012.5 | G76: =E76+F76 -> 25165 | H76: =$C$31 -> 3000 | I76: =G76-H76 -> 22165 | J76: =J75+I76 -> 47482.5
B77: 4 | C77: =$C$33 -> 2 | D77: =D76+C77 -> 8 | E77: =C77*$K$21 -> 6152.5 | F77: =D77*$I$21 -> 25350 | G77: =E77+F77 -> 31502.5 | H77: =$C$31 -> 3000 | I77: =G77-H77 -> 28502.5 | J77: =J76+I77 -> 75985
B78: 5 | C78: =$C$33 -> 2 | D78: =D77+C78 -> 10 | E78: =C78*$K$21 -> 6152.5 | F78: =D78*$I$21 -> 31687.5 | G78: =E78+F78 -> 37840 | H78: =$C$31 -> 3000 | I78: =G78-H78 -> 34840 | J78: =J77+I78 -> 110825
B79: 6 | C79: =$C$33 -> 2 | D79: =D78+C79 -> 12 | E79: =C79*$K$21 -> 6152.5 | F79: =D79*$I$21 -> 38025 | G79: =E79+F79 -> 44177.5 | H79: =$C$31 -> 3000 | I79: =G79-H79 -> 41177.5 | J79: =J78+I79 -> 152002.5
B80: 7 | C80: =$C$33 -> 2 | D80: =D79+C80 -> 14 | E80: =C80*$K$21 -> 6152.5 | F80: =D80*$I$21 -> 44362.5 | G80: =E80+F80 -> 50515 | H80: =$C$31 -> 3000 | I80: =G80-H80 -> 47515 | J80: =J79+I80 -> 199517.5
B81: 8 | C81: =$C$33 -> 2 | D81: =D80+C81 -> 16 | E81: =C81*$K$21 -> 6152.5 | F81: =D81*$I$21 -> 50700 | G81: =E81+F81 -> 56852.5 | H81: =$C$31 -> 3000 | I81: =G81-H81 -> 53852.5 | J81: =J80+I81 -> 253370
B82: 9 | C82: =$C$33 -> 2 | D82: =D81+C82 -> 18 | E82: =C82*$K$21 -> 6152.5 | F82: =D82*$I$21 -> 57037.5 | G82: =E82+F82 -> 63190 | H82: =$C$31 -> 3000 | I82: =G82-H82 -> 60190 | J82: =J81+I82 -> 313560
B83: 10 | C83: =$C$33 -> 2 | D83: =D82+C83 -> 20 | E83: =C83*$K$21 -> 6152.5 | F83: =D83*$I$21 -> 63375 | G83: =E83+F83 -> 69527.5 | H83: =$C$31 -> 3000 | I83: =G83-H83 -> 66527.5 | J83: =J82+I83 -> 380087.5
B84: 11 | C84: =$C$33 -> 2 | D84: =D83+C84 -> 22 | E84: =C84*$K$21 -> 6152.5 | F84: =D84*$I$21 -> 69712.5 | G84: =E84+F84 -> 75865 | H84: =$C$31 -> 3000 | I84: =G84-H84 -> 72865 | J84: =J83+I84 -> 452952.5
B85: 12 | C85: =$C$33 -> 2 | D85: =D84+C85 -> 24 | E85: =C85*$K$21 -> 6152.5 | F85: =D85*$I$21 -> 76050 | G85: =E85+F85 -> 82202.5 | H85: =$C$31 -> 3000 | I85: =G85-H85 -> 79202.5 | J85: =J84+I85 -> 532155
B86: 13 | C86: =$C$33 -> 2 | D86: =D85+C86 -> 26 | E86: =C86*$K$21 -> 6152.5 | F86: =D86*$I$21 -> 82387.5 | G86: =E86+F86 -> 88540 | H86: =$C$31 -> 3000 | I86: =G86-H86 -> 85540 | J86: =J85+I86 -> 617695
... B97: 24 | C97: =$C$33 -> 2 | D97: =D96+C97 -> 48 | E97: =C97*$K$21 -> 6152.5 | F97: =D97*$I$21 -> 152100 | G97: =E97+F97 -> 158252.5 | H97: =$C$31 -> 3000 | I97: =G97-H97 -> 155252.5 | J97: =J96+I97 -> 1976910
B100: AGGRESSIVE SCENARIO — Aggressive new customer(s)/month (detail)
B101: Month | C101: New Customers | D101: Cumulative Customers | E101: Onboarding Revenue | F101: Recurring License Revenue | G101: Total Revenue | H101: Fixed Opex (Mgd Svcs+Cloud) | I101: Net Cash Flow | J101: Cumulative Net Cash Flow
B102: 1 | C102: =$C$34 -> 3 | D102: =C102 -> 3 | E102: =C102*$K$21 -> 9228.75 | F102: =D102*$I$21 -> 9506.25 | G102: =E102+F102 -> 18735 | H102: =$C$31 -> 3000 | I102: =G102-H102 -> 15735 | J102: =I102 -> 15735
B103: 2 | C103: =$C$34 -> 3 | D103: =D102+C103 -> 6 | E103: =C103*$K$21 -> 9228.75 | F103: =D103*$I$21 -> 19012.5 | G103: =E103+F103 -> 28241.25 | H103: =$C$31 -> 3000 | I103: =G103-H103 -> 25241.25 | J103: =J102+I103 -> 40976.25
B104: 3 | C104: =$C$34 -> 3 | D104: =D103+C104 -> 9 | E104: =C104*$K$21 -> 9228.75 | F104: =D104*$I$21 -> 28518.75 | G104: =E104+F104 -> 37747.5 | H104: =$C$31 -> 3000 | I104: =G104-H104 -> 34747.5 | J104: =J103+I104 -> 75723.75
B105: 4 | C105: =$C$34 -> 3 | D105: =D104+C105 -> 12 | E105: =C105*$K$21 -> 9228.75 | F105: =D105*$I$21 -> 38025 | G105: =E105+F105 -> 47253.75 | H105: =$C$31 -> 3000 | I105: =G105-H105 -> 44253.75 | J105: =J104+I105 -> 119977.5
B106: 5 | C106: =$C$34 -> 3 | D106: =D105+C106 -> 15 | E106: =C106*$K$21 -> 9228.75 | F106: =D106*$I$21 -> 47531.25 | G106: =E106+F106 -> 56760 | H106: =$C$31 -> 3000 | I106: =G106-H106 -> 53760 | J106: =J105+I106 -> 173737.5
B107: 6 | C107: =$C$34 -> 3 | D107: =D106+C107 -> 18 | E107: =C107*$K$21 -> 9228.75 | F107: =D107*$I$21 -> 57037.5 | G107: =E107+F107 -> 66266.25 | H107: =$C$31 -> 3000 | I107: =G107-H107 -> 63266.25 | J107: =J106+I107 -> 237003.75
B108: 7 | C108: =$C$34 -> 3 | D108: =D107+C108 -> 21 | E108: =C108*$K$21 -> 9228.75 | F108: =D108*$I$21 -> 66543.75 | G108: =E108+F108 -> 75772.5 | H108: =$C$31 -> 3000 | I108: =G108-H108 -> 72772.5 | J108: =J107+I108 -> 309776.25
B109: 8 | C109: =$C$34 -> 3 | D109: =D108+C109 -> 24 | E109: =C109*$K$21 -> 9228.75 | F109: =D109*$I$21 -> 76050 | G109: =E109+F109 -> 85278.75 | H109: =$C$31 -> 3000 | I109: =G109-H109 -> 82278.75 | J109: =J108+I109 -> 392055
B110: 9 | C110: =$C$34 -> 3 | D110: =D109+C110 -> 27 | E110: =C110*$K$21 -> 9228.75 | F110: =D110*$I$21 -> 85556.25 | G110: =E110+F110 -> 94785 | H110: =$C$31 -> 3000 | I110: =G110-H110 -> 91785 | J110: =J109+I110 -> 483840
B111: 10 | C111: =$C$34 -> 3 | D111: =D110+C111 -> 30 | E111: =C111*$K$21 -> 9228.75 | F111: =D111*$I$21 -> 95062.5 | G111: =E111+F111 -> 104291.25 | H111: =$C$31 -> 3000 | I111: =G111-H111 -> 101291.25 | J111: =J110+I111 -> 585131.25
B112: 11 | C112: =$C$34 -> 3 | D112: =D111+C112 -> 33 | E112: =C112*$K$21 -> 9228.75 | F112: =D112*$I$21 -> 104568.75 | G112: =E112+F112 -> 113797.5 | H112: =$C$31 -> 3000 | I112: =G112-H112 -> 110797.5 | J112: =J111+I112 -> 695928.75
B113: 12 | C113: =$C$34 -> 3 | D113: =D112+C113 -> 36 | E113: =C113*$K$21 -> 9228.75 | F113: =D113*$I$21 -> 114075 | G113: =E113+F113 -> 123303.75 | H113: =$C$31 -> 3000 | I113: =G113-H113 -> 120303.75 | J113: =J112+I113 -> 816232.5
B114: 13 | C114: =$C$34 -> 3 | D114: =D113+C114 -> 39 | E114: =C114*$K$21 -> 9228.75 | F114: =D114*$I$21 -> 123581.25 | G114: =E114+F114 -> 132810 | H114: =$C$31 -> 3000 | I114: =G114-H114 -> 129810 | J114: =J113+I114 -> 946042.5
... B125: 24 | C125: =$C$34 -> 3 | D125: =D124+C125 -> 72 | E125: =C125*$K$21 -> 9228.75 | F125: =D125*$I$21 -> 228150 | G125: =E125+F125 -> 237378.75 | H125: =$C$31 -> 3000 | I125: =G125-H125 -> 234378.75 | J125: =J124+I125 -> 3001365
B128: Break-even month = first month in which cumulative net cash flow (recurring license revenue + one-time onboarding fees from new signings, minus the fixed monthly managed-services-and-cloud cost) equals or exceeds the one-time product-build investment. No churn, discounting, or customer-acquisition cost is modeled — treat this as a floor on payback speed, not a complete financial plan.

Sheet Methodology
A1: AI Prior Authorization Platform — Market Sizing
A2: Methodology, definitions, and sources — read this sheet first
A5: PRODUCT CONTEXT
B6: Product analyzed | C6: AI-powered prior authorization / utilization-management (UM) automation platform for healthcare providers and payers — comparable to ClearAuth AI (clearauthai.com).
B7: Geography | C7: United States (national + all 50 states + DC) and Canada (national + 10 provinces + 3 territories).
B8: Vertical | C8: Healthcare — hospitals & health systems, medical groups/specialty practices, ambulatory surgical centers, and payers (health plans) that run prior-authorization and utilization-review workflows.
A10: DEFINITIONS USED IN THIS MODEL
B11: TAM (Total Addressable Market) | C11: The total annual SOFTWARE/technology spend that a category-defining PA/UM automation platform could theoretically capture across all US + Canada payers and providers, if it owned 100% of the category.
B12: SAM (Serviceable Addressable Market) | C12: The slice of TAM that is realistically reachable given this product's go-to-market: mid-size to large hospitals/health systems, multi-site specialty groups, and payer UM departments, sold via direct/channel sales in English-language North American markets.
B13: SOM (Serviceable Obtainable Market) | C13: The realistic revenue a new entrant can capture within a 3–5 year horizon, given the existing competitive set (Cohere Health, Rhyme, Availity, Waystar, Myndshft, Banjo Health, XSOLIS, and EHR-native UM modules from Epic/Oracle Health).
A15: WHY A TWO-STAGE 'COST POOL → SOFTWARE TAM' MODEL
B16: The problem | C16: Prior authorization touches a very large pool of administrative COST (staff time, denials/appeals, delayed care) — but only a fraction of that cost converts into money that flows to a software vendor. A TAM built directly off total healthcare spend (e.g., "25% of $5T is administrative, therefore TAM = $1.3T") wildly overstates what a company can realistically sell into and will not withstand diligence.
B17: The fix | C17: This model first sizes the full PRIOR-AUTH/UM COST POOL top-down from national health expenditure (an easy number to defend), then applies a SOFTWARE-CAPTURE RATE — the share of that cost pool that historically converts into vendor license/subscription revenue in adjacent categories (RCM automation, claims automation, denial management SaaS) — to arrive at a Software TAM. SAM and SOM are then carved out of that Software TAM. Every conversion factor is an explicit, editable, labeled assumption on the Assumptions tab (yellow cells) — change any one and the whole model recalculates.
A19: SOURCES & GROUNDING (verify before client-facing use)
B20: US National Health Expenditure (NHE) | C20: CMS Office of the Actuary NHE Historical & Projections data. 2023 actual NHE was ~$4.87 trillion; this model projects 2025 at ~$5.4T using CMS's published ~7%/yr near-term trend growth rate. CONFIRM the latest published NHE figure at cms.gov before presenting.
B21: Canada National Health Expenditure | C21: Canadian Institute for Health Information (CIHI), National Health Expenditure Trends. 2024 estimate used here is CAD $372B. CONFIRM latest figure at cihi.ca.
B22: Administrative cost share of spend | C22: Widely-cited academic/health-policy estimates (e.g., Health Affairs, JAMA, NEJM Catalyst research on billing & insurance-related costs) place US administrative overhead at 15–30% of total health spend; this model uses 25% as a defensible mid/upper estimate reflecting the US's payer-fragmented system. Canada's single-payer provincial system is typically cited as materially lower (~15–18%); this model uses 17%.
B23: Prior-auth/UM share of admin cost | C23: CAQH CORE Index research tracks prior authorization as one of the costliest per-transaction administrative categories (alongside claims and eligibility). This model assumes PA/UM activities represent ~8% of total administrative cost — a placeholder assumption that should be refined against the latest CAQH Index report (caqh.org/core/index) before external use.
B24: Software-capture rate | C24: SaaS vendors in adjacent healthcare-admin-automation categories (denials management, RCM automation) typically price on value delivered, capturing roughly 10–15% of the underlying manual-cost pool as license/subscription fees. This model uses 12%.
B25: State/province apportionment | C25: US state weights = 2024 Census population estimate × a directional per-capita health-spending index (reflecting known patterns, e.g., higher per-capita spend in MA/NY/AK/DC, lower in UT/ID/NV). Canada province weights use 2024 population estimates with a smaller remoteness-cost adjustment for the territories. BOTH should be re-based on CMS's State Health Expenditure Accounts (cms.gov) and CIHI provincial data for a final client deliverable — the values here are directional, not official state-level statistics.
A27: HOW TO USE THIS WORKBOOK
B28: 1. | C28: Start on 'Assumptions' — every yellow cell is an editable lever. Change any of them (e.g., a more conservative software-capture rate) and every other tab recalculates automatically.
B29: 2. | C29: 'US National Model' and 'Canada National Model' show the full waterfall from national health spend down to TAM / SAM / SOM.
B30: 3. | C30: 'US State Breakdown' and 'Canada Province Breakdown' split those national totals across all states/provinces.
B31: 4. | C31: 'Executive Summary' is the one-page rollup — this is the tab to screenshot or present.
C33: This model was built without live web access in this session, so every dollar figure is drawn from general industry knowledge current to Jan 2026, not a fresh pull of the latest published reports. Before presenting to the client, re-verify: (a) the latest CMS NHE topline figure, (b) the latest CAQH CORE Index prior-auth statistics, and (c) any named-vendor market-share claims. Treat the numbers here as a rigorous, transparent MODEL — not as a quoted market-research figure.

Sheet Assumptions
A1: Key Assumptions
A2: Edit any yellow cell — every other tab recalculates from these inputs
B4: Assumption | C4: Value | D4: Note / Source
B5: US National Health Expenditure, 2025E ($B) | C5: 5400 | D5: CMS NHE Historical & Projections; 2023 actual $4,867B, projected fwd at ~7%/yr trend. VERIFY latest CMS figure.
B6: Canada National Health Expenditure, 2024E (CAD $B) | C6: 372 | D6: CIHI National Health Expenditure Trends. VERIFY latest CIHI figure.
B7: CAD → USD exchange rate | C7: 0.73 | D7: Illustrative FX rate — update to spot rate before presenting.
B8: US administrative cost, % of NHE | C8: 0.25 | D8: Health-policy literature range 15–30%; fragmented multi-payer system skews toward the higher end.
B9: Canada administrative cost, % of NHE | C9: 0.17 | D9: Single-payer provincial systems typically cited lower than the US.
B10: Prior-auth / UM share of administrative cost | C10: 0.08 | D10: Placeholder — refine against CAQH CORE Index prior-authorization cost data.
B11: Software-capture rate (cost pool → vendor software TAM) | C11: 0.12 | D11: Typical SaaS value-capture in adjacent RCM/denials-automation categories (~10–15%).
B12: SAM as % of Software TAM (reachable segment) | C12: 0.4 | D12: Reflects focus on hospitals/health systems + specialty groups + payer UM depts, direct/channel sales, NA English-language markets.
B13: SOM as % of SAM (3–5 year realistic capture) | C13: 0.015 | D13: Reasonable new-entrant share in a category with established players (Cohere Health, Rhyme, Availity, Waystar, Myndshft, XSOLIS).
B14: Optimistic SOM as % of SAM (upside case) | C14: 0.03 | D14: Upside case if the product wins a clear wedge (e.g., a specialty vertical or a flagship health-system logo) and expands faster.

Sheet US National Model
A1: United States — National TAM / SAM / SOM Waterfall
A2: All figures in USD $ billions unless noted. Formulas link to Assumptions tab.
B4: Line item | C4: $ Billions | D4: Formula logic
B5: 1. US National Health Expenditure (NHE) | C5: =Assumptions!$C$5 -> 5400 | D5: Total US healthcare spend, all payers, 2025E.
B6: 2. Administrative cost % of NHE | C6: =Assumptions!$C$8 -> 0.25 | D6: Billing, insurance-related, and utilization administration.
B7: 3. Total US healthcare administrative spend | C7: =C5*C6 -> 1350 | D7: Row 1 x Row 2.
B9: 4. Prior-auth / UM share of administrative cost | C9: =Assumptions!$C$10 -> 0.08 | D9: Placeholder — refine vs. CAQH CORE Index.
B10: 5. US Prior-Auth / UM COST POOL ('Problem TAM') | C10: =C7*C9 -> 108 | D10: Total cost currently spent (staff time + payer UM ops + denials/appeals) on PA/UM — NOT a software number.
B12: 6. Software-capture rate | C12: =Assumptions!$C$11 -> 0.12 | D12: Share of the cost pool that converts to vendor SaaS/license revenue.
B13: 7. US SOFTWARE TAM | C13: =C10*C12 -> 12.96 | D13: Row 5 x Row 6 — the realistic total software/tech spend category.
B15: 8. SAM as % of Software TAM | C15: =Assumptions!$C$12 -> 0.4 | D15: Reachable segment: hospitals/health systems, specialty groups, payer UM depts.
B16: 9. US SAM (Serviceable Addressable Market) | C16: =C13*C15 -> 5.184 | D16: Row 7 x Row 8.
B18: 10. Base-case SOM as % of SAM (3–5 yr) | C18: =Assumptions!$C$13 -> 0.015 | D18: Realistic new-entrant capture vs. established competitors.
B19: 11. US SOM — Base case | C19: =C16*C18 -> 0.07776 | D19: Row 9 x Row 10. Realistic 3-5yr revenue opportunity.
B20: 12. Optimistic SOM as % of SAM (upside) | C20: =Assumptions!$C$14 -> 0.03 | D20: Upside case with a strong wedge / flagship logo.
B21: 13. US SOM — Upside case | C21: =C16*C20 -> 0.15552 | D21: Row 9 x Row 12.

Sheet US State Breakdown
A1: United States — State-by-State TAM / SAM / SOM
A2: Apportioned from the US National Model using population share x a directional per-capita health-spend index. VERIFY against CMS State Health Expenditure Accounts before external use.
B4: State | C4: 2024E Population (M) | D4: Pop. Share | E4: Per-Capita Spend Index | F4: Weighted Share | G4: TAM ($M) | H4: SAM ($M) | I4: SOM — Base ($M) | J4: SOM — Upside ($M)
B5: California | C5: 39 | D5: =C5/SUM($C$5:$C$55) -> 0.11509517 | E5: 1.05 | F5: =D5*E5 -> 0.12084993 | G5: =($F5/$F$57)*'US National Model'!$C$13*1000 -> 1578.1651 | H5: =($F5/$F$57)*'US National Model'!$C$16*1000 -> 631.26605 | I5: =($F5/$F$57)*'US National Model'!$C$19*1000 -> 9.4689908 | J5: =($F5/$F$57)*'US National Model'!$C$21*1000 -> 18.937982
B6: Texas | C6: 31.3 | D6: =C6/SUM($C$5:$C$55) -> 0.092371256 | E6: 0.9 | F6: =D6*E6 -> 0.08313413 | G6: =($F6/$F$57)*'US National Model'!$C$13*1000 -> 1085.6389 | H6: =($F6/$F$57)*'US National Model'!$C$16*1000 -> 434.25555 | I6: =($F6/$F$57)*'US National Model'!$C$19*1000 -> 6.5138332 | J6: =($F6/$F$57)*'US National Model'!$C$21*1000 -> 13.027666
B7: Florida | C7: 23.4 | D7: =C7/SUM($C$5:$C$55) -> 0.069057105 | E7: 1.02 | F7: =D7*E7 -> 0.070438247 | G7: =($F7/$F$57)*'US National Model'!$C$13*1000 -> 919.84482 | H7: =($F7/$F$57)*'US National Model'!$C$16*1000 -> 367.93793 | I7: =($F7/$F$57)*'US National Model'!$C$19*1000 -> 5.5190689 | J7: =($F7/$F$57)*'US National Model'!$C$21*1000 -> 11.038138
B8: New York | C8: 19.9 | D8: =C8/SUM($C$5:$C$55) -> 0.058728051 | E8: 1.22 | F8: =D8*E8 -> 0.071648222 | G8: =($F8/$F$57)*'US National Model'!$C$13*1000 -> 935.64574 | H8: =($F8/$F$57)*'US National Model'!$C$16*1000 -> 374.2583 | I8: =($F8/$F$57)*'US National Model'!$C$19*1000 -> 5.6138745 | J8: =($F8/$F$57)*'US National Model'!$C$21*1000 -> 11.227749
B9: Pennsylvania | C9: 13.1 | D9: =C9/SUM($C$5:$C$55) -> 0.038660174 | E9: 1.05 | F9: =D9*E9 -> 0.040593183 | G9: =($F9/$F$57)*'US National Model'!$C$13*1000 -> 530.10162 | H9: =($F9/$F$57)*'US National Model'!$C$16*1000 -> 212.04065 | I9: =($F9/$F$57)*'US National Model'!$C$19*1000 -> 3.1806097 | J9: =($F9/$F$57)*'US National Model'!$C$21*1000 -> 6.3612195
B10: Illinois | C10: 12.6 | D10: =C10/SUM($C$5:$C$55) -> 0.037184595 | E10: 0.98 | F10: =D10*E10 -> 0.036440903 | G10: =($F10/$F$57)*'US National Model'!$C$13*1000 -> 475.87749 | H10: =($F10/$F$57)*'US National Model'!$C$16*1000 -> 190.35099 | I10: =($F10/$F$57)*'US National Model'!$C$19*1000 -> 2.8552649 | J10: =($F10/$F$57)*'US National Model'!$C$21*1000 -> 5.7105298
B11: Ohio | C11: 11.9 | D11: =C11/SUM($C$5:$C$55) -> 0.035118784 | E11: 1 | F11: =D11*E11 -> 0.035118784 | G11: =($F11/$F$57)*'US National Model'!$C$13*1000 -> 458.61209 | H11: =($F11/$F$57)*'US National Model'!$C$16*1000 -> 183.44484 | I11: =($F11/$F$57)*'US National Model'!$C$19*1000 -> 2.7516725 | J11: =($F11/$F$57)*'US National Model'!$C$21*1000 -> 5.5033451
B12: Georgia | C12: 11.2 | D12: =C12/SUM($C$5:$C$55) -> 0.033052973 | E12: 0.82 | F12: =D12*E12 -> 0.027103438 | G12: =($F12/$F$57)*'US National Model'!$C$13*1000 -> 353.94063 | H12: =($F12/$F$57)*'US National Model'!$C$16*1000 -> 141.57625 | I12: =($F12/$F$57)*'US National Model'!$C$19*1000 -> 2.1236438 | J12: =($F12/$F$57)*'US National Model'!$C$21*1000 -> 4.2472875
B13: North Carolina | C13: 11 | D13: =C13/SUM($C$5:$C$55) -> 0.032462742 | E13: 0.9 | F13: =D13*E13 -> 0.029216467 | G13: =($F13/$F$57)*'US National Model'!$C$13*1000 -> 381.53443 | H13: =($F13/$F$57)*'US National Model'!$C$16*1000 -> 152.61377 | I13: =($F13/$F$57)*'US National Model'!$C$19*1000 -> 2.2892066 | J13: =($F13/$F$57)*'US National Model'!$C$21*1000 -> 4.5784131
B14: Michigan | C14: 10.1 | D14: =C14/SUM($C$5:$C$55) -> 0.029806699 | E14: 1 | F14: =D14*E14 -> 0.029806699 | G14: =($F14/$F$57)*'US National Model'!$C$13*1000 -> 389.24219 | H14: =($F14/$F$57)*'US National Model'!$C$16*1000 -> 155.69688 | I14: =($F14/$F$57)*'US National Model'!$C$19*1000 -> 2.3354532 | J14: =($F14/$F$57)*'US National Model'!$C$21*1000 -> 4.6709063
B15: New Jersey | C15: 9.5 | D15: =C15/SUM($C$5:$C$55) -> 0.028036004 | E15: 1.1 | F15: =D15*E15 -> 0.030839605 | G15: =($F15/$F$57)*'US National Model'!$C$13*1000 -> 402.73079 | H15: =($F15/$F$57)*'US National Model'!$C$16*1000 -> 161.09231 | I15: =($F15/$F$57)*'US National Model'!$C$19*1000 -> 2.4163847 | J15: =($F15/$F$57)*'US National Model'!$C$21*1000 -> 4.8327694
B16: Virginia | C16: 8.8 | D16: =C16/SUM($C$5:$C$55) -> 0.025970193 | E16: 0.92 | F16: =D16*E16 -> 0.023892578 | G16: =($F16/$F$57)*'US National Model'!$C$13*1000 -> 312.01038 | H16: =($F16/$F$57)*'US National Model'!$C$16*1000 -> 124.80415 | I16: =($F16/$F$57)*'US National Model'!$C$19*1000 -> 1.8720623 | J16: =($F16/$F$57)*'US National Model'!$C$21*1000 -> 3.7441245
... B55: District of Columbia | C55: 0.68 | D55: =C55/SUM($C$5:$C$55) -> 0.0020067877 | E55: 1.9 | F55: =D55*E55 -> 0.0038128966 | G55: =($F55/$F$57)*'US National Model'!$C$13*1000 -> 49.79217 | H55: =($F55/$F$57)*'US National Model'!$C$16*1000 -> 19.916868 | I55: =($F55/$F$57)*'US National Model'!$C$19*1000 -> 0.29875302 | J55: =($F55/$F$57)*'US National Model'!$C$21*1000 -> 0.59750604
B57: TOTAL (sum of weighted shares — used to normalize) | F57: =SUM(F5:F55) -> 0.99242792
B58: US TOTAL (all 50 states + DC) | G58: =SUM(G5:G55) -> 12960 | H58: =SUM(H5:H55) -> 5184 | I58: =SUM(I5:I55) -> 77.76 | J58: =SUM(J5:J55) -> 155.52

Sheet Canada National Model
A1: Canada — National TAM / SAM / SOM Waterfall
A2: Figures shown in CAD and USD billions. Formulas link to Assumptions tab.
B4: Line item | C4: CAD $B | D4: USD $B | E4: Formula logic
B5: 1. Canada National Health Expenditure (NHE) | C5: =Assumptions!$C$6 -> 372 | D5: =C5*Assumptions!$C$7 -> 271.56 | E5: Total Canada healthcare spend, all payers/provinces, 2024E.
B6: 2. Administrative cost % of NHE | C6: =Assumptions!$C$9 -> 0.17 | D6: =C6 -> 0.17 | E6: Lower than US — single-payer provincial systems.
B7: 3. Total Canada healthcare administrative spend | C7: =C5*C6 -> 63.24 | D7: =D5*D6 -> 46.1652 | E7: Row 1 x Row 2.
B9: 4. Prior-auth / UM share of administrative cost | C9: =Assumptions!$C$10 -> 0.08 | D9: =C9 -> 0.08 | E9: Same placeholder share as US model.
B10: 5. Canada Prior-Auth / UM COST POOL ('Problem TAM') | C10: =C7*C9 -> 5.0592 | D10: =D7*D9 -> 3.693216 | E10: Total cost currently spent on PA/UM across Canada — not a software number.
B12: 6. Software-capture rate | C12: =Assumptions!$C$11 -> 0.12 | D12: =C12 -> 0.12 | E12: Same capture-rate assumption as US model.
B13: 7. Canada SOFTWARE TAM | C13: =C10*C12 -> 0.607104 | D13: =D10*D12 -> 0.44318592 | E13: Row 5 x Row 6.
B15: 8. SAM as % of Software TAM | C15: =Assumptions!$C$12 -> 0.4 | D15: =C15 -> 0.4 | E15: Same reachable-segment assumption as US model.
B16: 9. Canada SAM (Serviceable Addressable Market) | C16: =C13*C15 -> 0.2428416 | D16: =D13*D15 -> 0.17727437 | E16: Row 7 x Row 8.
B18: 10. Base-case SOM as % of SAM (3–5 yr) | C18: =Assumptions!$C$13 -> 0.015 | D18: =C18 -> 0.015 | E18: Realistic new-entrant capture.
B19: 11. Canada SOM — Base case | C19: =C16*C18 -> 0.003642624 | D19: =D16*D18 -> 0.0026591155 | E19: Row 9 x Row 10.
B20: 12. Optimistic SOM as % of SAM (upside) | C20: =Assumptions!$C$14 -> 0.03 | D20: =C20 -> 0.03 | E20: Upside case.
B21: 13. Canada SOM — Upside case | C21: =C16*C20 -> 0.007285248 | D21: =D16*D20 -> 0.005318231 | E21: Row 9 x Row 12.

Sheet Canada Province Breakdown
A1: Canada — Province/Territory TAM / SAM / SOM
A2: Apportioned from the Canada National Model using population share x a directional per-capita health-spend index (higher for the territories, reflecting remote-care delivery cost). VERIFY against CIHI provincial data before external use.
B4: Province / Territory | C4: 2024E Population (M) | D4: Pop. Share | E4: Per-Capita Spend Index | F4: Weighted Share | G4: TAM (US$M) | H4: SAM (US$M) | I4: SOM — Base (US$M) | J4: SOM — Upside (US$M)
B5: Ontario | C5: 15.8 | D5: =C5/SUM($C$5:$C$17) -> 0.38963281 | E5: 0.95 | F5: =D5*E5 -> 0.37015117 | G5: =($F5/$F$19)*'Canada National Model'!$D$13*1000 -> 165.15808 | H5: =($F5/$F$19)*'Canada National Model'!$D$16*1000 -> 66.063232 | I5: =($F5/$F$19)*'Canada National Model'!$D$19*1000 -> 0.99094848 | J5: =($F5/$F$19)*'Canada National Model'!$D$21*1000 -> 1.981897
B6: Quebec | C6: 8.9 | D6: =C6/SUM($C$5:$C$17) -> 0.21947671 | E6: 1 | F6: =D6*E6 -> 0.21947671 | G6: =($F6/$F$19)*'Canada National Model'!$D$13*1000 -> 97.928509 | H6: =($F6/$F$19)*'Canada National Model'!$D$16*1000 -> 39.171404 | I6: =($F6/$F$19)*'Canada National Model'!$D$19*1000 -> 0.58757105 | J6: =($F6/$F$19)*'Canada National Model'!$D$21*1000 -> 1.1751421
B7: British Columbia | C7: 5.6 | D7: =C7/SUM($C$5:$C$17) -> 0.1380977 | E7: 1 | F7: =D7*E7 -> 0.1380977 | G7: =($F7/$F$19)*'Canada National Model'!$D$13*1000 -> 61.617938 | H7: =($F7/$F$19)*'Canada National Model'!$D$16*1000 -> 24.647175 | I7: =($F7/$F$19)*'Canada National Model'!$D$19*1000 -> 0.36970763 | J7: =($F7/$F$19)*'Canada National Model'!$D$21*1000 -> 0.73941526
B8: Alberta | C8: 4.8 | D8: =C8/SUM($C$5:$C$17) -> 0.11836946 | E8: 0.98 | F8: =D8*E8 -> 0.11600207 | G8: =($F8/$F$19)*'Canada National Model'!$D$13*1000 -> 51.759068 | H8: =($F8/$F$19)*'Canada National Model'!$D$16*1000 -> 20.703627 | I8: =($F8/$F$19)*'Canada National Model'!$D$19*1000 -> 0.31055441 | J8: =($F8/$F$19)*'Canada National Model'!$D$21*1000 -> 0.62110882
B9: Manitoba | C9: 1.5 | D9: =C9/SUM($C$5:$C$17) -> 0.036990456 | E9: 1.05 | F9: =D9*E9 -> 0.038839979 | G9: =($F9/$F$19)*'Canada National Model'!$D$13*1000 -> 17.330045 | H9: =($F9/$F$19)*'Canada National Model'!$D$16*1000 -> 6.932018 | I9: =($F9/$F$19)*'Canada National Model'!$D$19*1000 -> 0.10398027 | J9: =($F9/$F$19)*'Canada National Model'!$D$21*1000 -> 0.20796054
B10: Saskatchewan | C10: 1.2 | D10: =C10/SUM($C$5:$C$17) -> 0.029592365 | E10: 1.05 | F10: =D10*E10 -> 0.031071983 | G10: =($F10/$F$19)*'Canada National Model'!$D$13*1000 -> 13.864036 | H10: =($F10/$F$19)*'Canada National Model'!$D$16*1000 -> 5.5456144 | I10: =($F10/$F$19)*'Canada National Model'!$D$19*1000 -> 0.083184217 | J10: =($F10/$F$19)*'Canada National Model'!$D$21*1000 -> 0.16636843
B11: Nova Scotia | C11: 1.05 | D11: =C11/SUM($C$5:$C$17) -> 0.02589332 | E11: 1.1 | F11: =D11*E11 -> 0.028482651 | G11: =($F11/$F$19)*'Canada National Model'!$D$13*1000 -> 12.7087 | H11: =($F11/$F$19)*'Canada National Model'!$D$16*1000 -> 5.0834799 | I11: =($F11/$F$19)*'Canada National Model'!$D$19*1000 -> 0.076252198 | J11: =($F11/$F$19)*'Canada National Model'!$D$21*1000 -> 0.1525044
B12: New Brunswick | C12: 0.85 | D12: =C12/SUM($C$5:$C$17) -> 0.020961259 | E12: 1.08 | F12: =D12*E12 -> 0.022638159 | G12: =($F12/$F$19)*'Canada National Model'!$D$13*1000 -> 10.100941 | H12: =($F12/$F$19)*'Canada National Model'!$D$16*1000 -> 4.0403762 | I12: =($F12/$F$19)*'Canada National Model'!$D$19*1000 -> 0.060605643 | J12: =($F12/$F$19)*'Canada National Model'!$D$21*1000 -> 0.12121129
B13: Newfoundland & Labrador | C13: 0.54 | D13: =C13/SUM($C$5:$C$17) -> 0.013316564 | E13: 1.25 | F13: =D13*E13 -> 0.016645705 | G13: =($F13/$F$19)*'Canada National Model'!$D$13*1000 -> 7.4271622 | H13: =($F13/$F$19)*'Canada National Model'!$D$16*1000 -> 2.9708649 | I13: =($F13/$F$19)*'Canada National Model'!$D$19*1000 -> 0.044562973 | J13: =($F13/$F$19)*'Canada National Model'!$D$21*1000 -> 0.089125946
B14: Prince Edward Island | C14: 0.18 | D14: =C14/SUM($C$5:$C$17) -> 0.0044388548 | E14: 1.1 | F14: =D14*E14 -> 0.0048827403 | G14: =($F14/$F$19)*'Canada National Model'!$D$13*1000 -> 2.1786342 | H14: =($F14/$F$19)*'Canada National Model'!$D$16*1000 -> 0.8714537 | I14: =($F14/$F$19)*'Canada National Model'!$D$19*1000 -> 0.013071805 | J14: =($F14/$F$19)*'Canada National Model'!$D$21*1000 -> 0.026143611
B15: Northwest Territories | C15: 0.045 | D15: =C15/SUM($C$5:$C$17) -> 0.0011097137 | E15: 2.2 | F15: =D15*E15 -> 0.0024413701 | G15: =($F15/$F$19)*'Canada National Model'!$D$13*1000 -> 1.0893171 | H15: =($F15/$F$19)*'Canada National Model'!$D$16*1000 -> 0.43572685 | I15: =($F15/$F$19)*'Canada National Model'!$D$19*1000 -> 0.0065359027 | J15: =($F15/$F$19)*'Canada National Model'!$D$21*1000 -> 0.013071805
B16: Yukon | C16: 0.045 | D16: =C16/SUM($C$5:$C$17) -> 0.0011097137 | E16: 1.9 | F16: =D16*E16 -> 0.002108456 | G16: =($F16/$F$19)*'Canada National Model'!$D$13*1000 -> 0.94077388 | H16: =($F16/$F$19)*'Canada National Model'!$D$16*1000 -> 0.37630955 | I16: =($F16/$F$19)*'Canada National Model'!$D$19*1000 -> 0.0056446433 | J16: =($F16/$F$19)*'Canada National Model'!$D$21*1000 -> 0.011289287
B17: Nunavut | C17: 0.041 | D17: =C17/SUM($C$5:$C$17) -> 0.0010110725 | E17: 2.4 | F17: =D17*E17 -> 0.0024265739 | G17: =($F17/$F$19)*'Canada National Model'!$D$13*1000 -> 1.0827152 | H17: =($F17/$F$19)*'Canada National Model'!$D$16*1000 -> 0.43308608 | I17: =($F17/$F$19)*'Canada National Model'!$D$19*1000 -> 0.0064962912 | J17: =($F17/$F$19)*'Canada National Model'!$D$21*1000 -> 0.012992582
B19: TOTAL (sum of weighted shares — used to normalize) | F19: =SUM(F5:F17) -> 0.99326527
B20: CANADA TOTAL (all provinces + territories) | G20: =SUM(G5:G17) -> 443.18592 | H20: =SUM(H5:H17) -> 177.27437 | I20: =SUM(I5:I17) -> 2.6591155 | J20: =SUM(J5:J17) -> 5.318231
